setup.py
alibabacloud_darabonba_encode_util/__init__.py
alibabacloud_darabonba_encode_util/encoder.py
alibabacloud_darabonba_encode_util/sm3.py
alibabacloud_darabonba_encode_util_py2.egg-info/PKG-INFO
alibabacloud_darabonba_encode_util_py2.egg-info/SOURCES.txt
alibabacloud_darabonba_encode_util_py2.egg-info/dependency_links.txt
alibabacloud_darabonba_encode_util_py2.egg-info/top_level.txt