Metadata-Version: 2.1
Name: alibabacloud-darabonba-encode-util-py2
Version: 0.0.1
Summary: Darabonba Util Library for Alibaba Cloud Python2 SDK
Home-page: https://github.com/aliyun/darabonba-crypto-util
Author: Alibaba Cloud SDK
Author-email: sdk-darabonbam@alibabacloud.com
License: Apache License 2.0
Keywords: alibabacloud,darabonba,encode,util,py2
Platform: any
Classifier: Development Status :: 4 - Beta
Classifier: Intended Audience :: Developers
Classifier: License :: OSI Approved :: Apache Software License
Classifier: Programming Language :: Python
Classifier: Programming Language :: Python :: 2
Classifier: Programming Language :: Python :: 2.7
Classifier: Programming Language :: Python :: 3
Classifier: Programming Language :: Python :: 3.4
Classifier: Programming Language :: Python :: 3.5
Classifier: Programming Language :: Python :: 3.6
Classifier: Programming Language :: Python :: 3.7
Classifier: Programming Language :: Python :: 3.8
Classifier: Topic :: Software Development
